LICENSE
MANIFEST.in
README.md
setup.cfg
setup.py
django_email_center/__init__.py
django_email_center/admin.py
django_email_center/apps.py
django_email_center/meta.py
django_email_center.egg-info/PKG-INFO
django_email_center.egg-info/SOURCES.txt
django_email_center.egg-info/dependency_links.txt
django_email_center.egg-info/top_level.txt
django_email_center/migrations/0001_initial.py
django_email_center/migrations/__init__.py
django_email_center/models/Email.py
django_email_center/models/__init__.py
django_email_center/models/choices.py
django_email_center/utils/__init__.py
django_email_center/utils/actions.py
django_email_center/views/__init__.py
django_email_center/views/email_center.py