Metadata-Version: 1.0
Name: django-email-center
Version: 0.0.3
Summary: The "Django Email Center" is a solutions for send your email(s)
Home-page: https://github.com/shinneider/django_email_center
Author: Shinneider Libanio da Silva
Author-email: shinneider-libanio@hotmail.com
License: MIT
Platform: UNKNOWN
